pypi_test_app/__init__.py
pypi_test_app/__main__.py
pypi_test_app/cli.py
pypi_test_app/database.py
pypi_test_app/main.py
pypi_test_app/models.py
pypi_test_app/pdf_processing.py
pypi_test_app/schemas.py
pypi_test_app/seed_data.py
pypi_test_app/storage.py
pypi_test_app/api/__init__.py
pypi_test_app/api/dependencies.py
pypi_test_app/api/routes.py
pypi_test_app/static/index.html
pypi_test_app/static/vite.svg
pypi_test_app/static/assets/index-BZ29wlRN.css
pypi_test_app/static/assets/index-CwS5OJKv.js
pypi_upload_demo-0.1.4.dist-info/METADATA
pypi_upload_demo-0.1.4.dist-info/WHEEL
pypi_upload_demo-0.1.4.dist-info/entry_points.txt
pypi_upload_demo-0.1.4.dist-info/top_level.txt
pypi_upload_demo-0.1.4.dist-info/RECORD
