Metadata-Version: 2.4
Name: pypi-upload-demo
Version: 0.1.4
Summary: FastAPI + React file upload demo packaged for PyPI distribution
Home-page: https://example.com/pypi-upload-demo
Author: Your Name
Classifier: Programming Language :: Python :: 3
Classifier: Framework :: FastAPI
Classifier: License :: OSI Approved :: MIT License
Classifier: Operating System :: OS Independent
Requires-Python: >=3.10
Requires-Dist: fastapi>=0.115.5
Requires-Dist: numpy>=1.24
Requires-Dist: opencv-python-headless>=4.8
Requires-Dist: Pillow>=10.0
Requires-Dist: PyMuPDF>=1.24.0
Requires-Dist: PyPDF2>=3.0.0
Requires-Dist: SQLAlchemy>=2.0
Requires-Dist: aiosqlite>=0.19
Requires-Dist: uvicorn>=0.32.1
Requires-Dist: python-multipart>=0.0.20
Dynamic: author
Dynamic: classifier
Dynamic: description
Dynamic: description-content-type
Dynamic: home-page
Dynamic: requires-dist
Dynamic: requires-python
Dynamic: summary
